Workbook

Sheet Summary
A1: This project involved answering questions from a large movie dataset to find changes in revenue over time, trends with certain genres, ratings, and scores. Gross revenue generally increased from 1980 to 2019 with some minor year to year fluctuations, and before the sharp decline in 2020 due to the COVID-19 pandemic that affected the entire movie industry. The data showed that older movie revenues require a much larger inflation adjustment. It narrows more with recent releases. Movies with higher scores do not appear to have a strong relationship with gross relative to budget. The ratio remains relatively flat across the board with a few outliers. R-Rated films generated approximately 2.55 times their budget in gross revenue, but not have the highest gross relative to budget. Smaller sample sizes with TV-MA and Not Rated movies should be interpreted with caution despite the higher ratios. Among the genres, action films had the highest gross relative budget at 2.93, followed by Comedy at 2.84, and Drama at 2.83.

Sheet PivotTable
A3: year | B3: Sum of gross
A4: 1980 | B4: 2483666964
A5: 1981 | B5: 2520064889
A6: 1982 | B6: 3187580517
A7: 1983 | B7: 2750004626
A8: 1984 | B8: 3533092196
A9: 1985 | B9: 3691509283
A10: 1986 | B10: 3647511836
A11: 1987 | B11: 4033434255
A12: 1988 | B12: 4840385631
A13: 1989 | B13: 6087250779
A14: 1990 | B14: 6804235860
A15: 1991 | B15: 6254770668
... A44: 2020 | B44: 2848298792
A45: (blank)
A46: Grand Total | B46: 587105546272

Sheet Revenue Analysis
A3: year | B3: Sum of gross | C3: Sum of budget | F3: year | G3: Gross relative to budget
A4: 1980 | B4: 2483666964 | C4: 568850000 | F4: =A4 -> 1980 | G4: =B4 / C4 -> 4.3661193
A5: 1981 | B5: 2520064889 | C5: 709450000 | F5: =A5 -> 1981 | G5: =B5 / C5 -> 3.5521388
A6: 1982 | B6: 3187580517 | C6: 836670000 | F6: =A6 -> 1982 | G6: =B6 / C6 -> 3.809842
A7: 1983 | B7: 2750004626 | C7: 893975562 | F7: =A7 -> 1983 | G7: =B7 / C7 -> 3.0761519
A8: 1984 | B8: 3533092196 | C8: 1116326000 | F8: =A8 -> 1984 | G8: =B8 / C8 -> 3.1649287
A9: 1985 | B9: 3691509283 | C9: 1220510000 | F9: =A9 -> 1985 | G9: =B9 / C9 -> 3.0245629
A10: 1986 | B10: 3647511836 | C10: 1264787376 | F10: =A10 -> 1986 | G10: =B10 / C10 -> 2.8838933
A11: 1987 | B11: 4033434255 | C11: 1382542678 | F11: =A11 -> 1987 | G11: =B11 / C11 -> 2.9174031
A12: 1988 | B12: 4840385631 | C12: 1730540000 | F12: =A12 -> 1988 | G12: =B12 / C12 -> 2.7970377
A13: 1989 | B13: 6087250779 | C13: 1784762578 | F13: =A13 -> 1989 | G13: =B13 / C13 -> 3.4106782
A14: 1990 | B14: 6804235860 | C14: 2072503000 | F14: =A14 -> 1990 | G14: =B14 / C14 -> 3.2831006
A15: 1991 | B15: 6254770668 | C15: 2268248000 | F15: =A15 -> 1991 | G15: =B15 / C15 -> 2.7575339
... A44: 2020 | B44: 2848298792 | C44: 862965750 | F44: =A44 -> 2020 | G44: =B44 / C44 -> 3.3005931
A45: (blank)
A46: Grand Total | B46: 587105546272 | C46: 195637549431

Sheet CPI
A1: Year | B1: Annual Average CPI
A2: 1913 | B2: 9.9
A3: 1914 | B3: 10
A4: 1915 | B4: 10.1
A5: 1916 | B5: 10.9
A6: 1917 | B6: 12.8
A7: 1918 | B7: 15
A8: 1919 | B8: 17.3
A9: 1920 | B9: 20
A10: 1921 | B10: 17.9
A11: 1922 | B11: 16.8
A12: 1923 | B12: 17.1
A13: 1924 | B13: 17.1
... A114: 2025 | B114: 321.9
A115: 2026* | B115: 334.4

Sheet Movies
A1: name | B1: rating | C1: genre | D1: year | E1: released | F1: score | G1: votes | H1: director | I1: writer | J1: star | K1: country | L1: budget | M1: gross | N1: company | O1: runtime | P1: cpi of release year | Q1: gross revenue in 2023 dollars
A2: The Shining | B2: R | C2: Drama | D2: 1980 | E2: June 13, 1980 (United States) | F2: 8.4 | G2: 927000 | H2: Stanley Kubrick | I2: Stephen King | J2: Jack Nicholson | K2: United Kingdom | L2: 19000000 | M2: 46998772 | N2: Warner Bros. | O2: 146 | P2: {=_xlfn.XLOOKUP(D2, CPI!$A:A, CPI!$B:B)} -> 82.4 | Q2: =IF(M2="","",PRODUCT(M2,CPI!$B$112/P2)) -> 1.7379279e+08
A3: The Blue Lagoon | B3: R | C3: Adventure | D3: 1980 | E3: July 2, 1980 (United States) | F3: 5.8 | G3: 65000 | H3: Randal Kleiser | I3: Henry De Vere Stacpoole | J3: Brooke Shields | K3: United States | L3: 4500000 | M3: 58853106 | N3: Columbia Pictures | O3: 104 | P3: {=_xlfn.XLOOKUP(D3, CPI!$A:A, CPI!$B:B)} -> 82.4 | Q3: =IF(M3="","",PRODUCT(M3,CPI!$B$112/P3)) -> 2.1762793e+08
A4: Star Wars: Episode V - The Empire Strikes Back | B4: PG | C4: Action | D4: 1980 | E4: June 20, 1980 (United States) | F4: 8.7 | G4: 1200000 | H4: Irvin Kershner | I4: Leigh Brackett | J4: Mark Hamill | K4: United States | L4: 18000000 | M4: 538375067 | N4: Lucasfilm | O4: 124 | P4: {=_xlfn.XLOOKUP(D4, CPI!$A:A, CPI!$B:B)} -> 82.4 | Q4: =IF(M4="","",PRODUCT(M4,CPI!$B$112/P4)) -> 1.9908117e+09
A5: Airplane! | B5: PG | C5: Comedy | D5: 1980 | E5: July 2, 1980 (United States) | F5: 7.7 | G5: 221000 | H5: Jim Abrahams | I5: Jim Abrahams | J5: Robert Hays | K5: United States | L5: 3500000 | M5: 83453539 | N5: Paramount Pictures | O5: 88 | P5: {=_xlfn.XLOOKUP(D5, CPI!$A:A, CPI!$B:B)} -> 82.4 | Q5: =IF(M5="","",PRODUCT(M5,CPI!$B$112/P5)) -> 3.0859579e+08
A6: Caddyshack | B6: R | C6: Comedy | D6: 1980 | E6: July 25, 1980 (United States) | F6: 7.3 | G6: 108000 | H6: Harold Ramis | I6: Brian Doyle-Murray | J6: Chevy Chase | K6: United States | L6: 6000000 | M6: 39846344 | N6: Orion Pictures | O6: 98 | P6: {=_xlfn.XLOOKUP(D6, CPI!$A:A, CPI!$B:B)} -> 82.4 | Q6: =IF(M6="","",PRODUCT(M6,CPI!$B$112/P6)) -> 1.4734443e+08
A7: Friday the 13th | B7: R | C7: Horror | D7: 1980 | E7: May 9, 1980 (United States) | F7: 6.4 | G7: 123000 | H7: Sean S. Cunningham | I7: Victor Miller | J7: Betsy Palmer | K7: United States | L7: 550000 | M7: 39754601 | N7: Paramount Pictures | O7: 95 | P7: {=_xlfn.XLOOKUP(D7, CPI!$A:A, CPI!$B:B)} -> 82.4 | Q7: =IF(M7="","",PRODUCT(M7,CPI!$B$112/P7)) -> 1.4700518e+08
A8: The Blues Brothers | B8: R | C8: Action | D8: 1980 | E8: June 20, 1980 (United States) | F8: 7.9 | G8: 188000 | H8: John Landis | I8: Dan Aykroyd | J8: John Belushi | K8: United States | L8: 27000000 | M8: 115229890 | N8: Universal Pictures | O8: 133 | P8: {=_xlfn.XLOOKUP(D8, CPI!$A:A, CPI!$B:B)} -> 82.4 | Q8: =IF(M8="","",PRODUCT(M8,CPI!$B$112/P8)) -> 4.2609888e+08
A9: Raging Bull | B9: R | C9: Biography | D9: 1980 | E9: December 19, 1980 (United States) | F9: 8.2 | G9: 330000 | H9: Martin Scorsese | I9: Jake LaMotta | J9: Robert De Niro | K9: United States | L9: 18000000 | M9: 23402427 | N9: Chartoff-Winkler Productions | O9: 129 | P9: {=_xlfn.XLOOKUP(D9, CPI!$A:A, CPI!$B:B)} -> 82.4 | Q9: =IF(M9="","",PRODUCT(M9,CPI!$B$112/P9)) -> 86537858
A10: Superman II | B10: PG | C10: Action | D10: 1980 | E10: June 19, 1981 (United States) | F10: 6.8 | G10: 101000 | H10: Richard Lester | I10: Jerry Siegel | J10: Gene Hackman | K10: United States | L10: 54000000 | M10: 108185706 | N10: Dovemead Films | O10: 127 | P10: {=_xlfn.XLOOKUP(D10, CPI!$A:A, CPI!$B:B)} -> 82.4 | Q10: =IF(M10="","",PRODUCT(M10,CPI!$B$112/P10)) -> 4.0005078e+08
A11: The Long Riders | B11: R | C11: Biography | D11: 1980 | E11: May 16, 1980 (United States) | F11: 7 | G11: 10000 | H11: Walter Hill | I11: Bill Bryden | J11: David Carradine | K11: United States | L11: 10000000 | M11: 15795189 | N11: United Artists | O11: 100 | P11: {=_xlfn.XLOOKUP(D11, CPI!$A:A, CPI!$B:B)} -> 82.4 | Q11: =IF(M11="","",PRODUCT(M11,CPI!$B$112/P11)) -> 58407695
A12: Any Which Way You Can | B12: PG | C12: Action | D12: 1980 | E12: December 17, 1980 (United States) | F12: 6.1 | G12: 18000 | H12: Buddy Van Horn | I12: Stanford Sherman | J12: Clint Eastwood | K12: United States | L12: 15000000 | M12: 70687344 | N12: The Malpaso Company | O12: 116 | P12: {=_xlfn.XLOOKUP(D12, CPI!$A:A, CPI!$B:B)} -> 82.4 | Q12: =IF(M12="","",PRODUCT(M12,CPI!$B$112/P12)) -> 2.6138876e+08
A13: The Gods Must Be Crazy | B13: PG | C13: Adventure | D13: 1980 | E13: October 26, 1984 (United States) | F13: 7.3 | G13: 54000 | H13: Jamie Uys | I13: Jamie Uys | J13: N!xau | K13: South Africa | L13: 5000000 | M13: 30031783 | N13: C.A.T. Films | O13: 109 | P13: {=_xlfn.XLOOKUP(D13, CPI!$A:A, CPI!$B:B)} -> 82.4 | Q13: =IF(M13="","",PRODUCT(M13,CPI!$B$112/P13)) -> 1.1105199e+08
... A17: Somewhere in Time | B17: PG | C17: Drama | D17: 1980 | E17: October 3, 1980 (United States) | F17: 7.2 | G17: 27000 | H17: Jeannot Szwarc | I17: Richard Matheson | J17: Christopher Reeve | K17: United States | L17: 5100000 | M17: 9709597 | N17: Rastar Pictures | O17: 103 | P17: {=_xlfn.XLOOKUP(D17, CPI!$A:A, CPI!$B:B)} -> 82.4 | Q17: =IF(M17="","",PRODUCT(M17,CPI!$B$112/P17)) -> 35904299
A18: Fame | B18: R | C18: Drama | D18: 1980 | E18: May 16, 1980 (United States) | F18: 6.6 | G18: 21000 | H18: Alan Parker | I18: Christopher Gore | J18: Eddie Barth | K18: United States | M18: 21202829 | N18: Metro-Goldwyn-Mayer (MGM) | O18: 134 | P18: {=_xlfn.XLOOKUP(D18, CPI!$A:A, CPI!$B:B)} -> 82.4 | Q18: =IF(M18="","",PRODUCT(M18,CPI!$B$112/P18)) -> 78404150
A19: 9 to 5 | B19: PG | C19: Comedy | D19: 1980 | E19: December 19, 1980 (United States) | F19: 6.9 | G19: 29000 | H19: Colin Higgins | I19: Patricia Resnick | J19: Jane Fonda | K19: United States | L19: 10000000 | M19: 103300686 | N19: IPC Films | O19: 109 | P19: {=_xlfn.XLOOKUP(D19, CPI!$A:A, CPI!$B:B)} -> 82.4 | Q19: =IF(M19="","",PRODUCT(M19,CPI!$B$112/P19)) -> 3.8198688e+08
A20: The Fog | B20: R | C20: Horror | D20: 1980 | E20: February 8, 1980 (United States) | F20: 6.8 | G20: 66000 | H20: John Carpenter | I20: John Carpenter | J20: Adrienne Barbeau | K20: United States | L20: 1000000 | M20: 21448782 | N20: AVCO Embassy Pictures | O20: 89 | P20: {=_xlfn.XLOOKUP(D20, CPI!$A:A, CPI!$B:B)} -> 82.4 | Q20: =IF(M20="","",PRODUCT(M20,CPI!$B$112/P20)) -> 79313639
A21: Stir Crazy | B21: R | C21: Comedy | D21: 1980 | E21: December 12, 1980 (United States) | F21: 6.8 | G21: 26000 | H21: Sidney Poitier | I21: Bruce Jay Friedman | J21: Gene Wilder | K21: United States | M21: 101300000 | N21: Columbia Pictures | O21: 111 | P21: {=_xlfn.XLOOKUP(D21, CPI!$A:A, CPI!$B:B)} -> 82.4 | Q21: =IF(M21="","",PRODUCT(M21,CPI!$B$112/P21)) -> 3.7458871e+08
A22: Cruising | B22: R | C22: Crime | D22: 1980 | E22: February 15, 1980 (United States) | F22: 6.5 | G22: 20000 | H22: William Friedkin | I22: William Friedkin | J22: Al Pacino | K22: West Germany | L22: 11000000 | M22: 19814523 | N22: Lorimar Film Entertainment | O22: 102 | P22: {=_xlfn.XLOOKUP(D22, CPI!$A:A, CPI!$B:B)} -> 82.4 | Q22: =IF(M22="","",PRODUCT(M22,CPI!$B$112/P22)) -> 73270451
A23: Heaven's Gate | B23: R | C23: Adventure | D23: 1980 | E23: April 24, 1981 (United States) | F23: 6.8 | G23: 14000 | H23: Michael Cimino | I23: Michael Cimino | J23: Kris Kristofferson | K23: United States | L23: 44000000 | M23: 3484523 | N23: Partisan Productions | O23: 219 | P23: {=_xlfn.XLOOKUP(D23, CPI!$A:A, CPI!$B:B)} -> 82.4 | Q23: =IF(M23="","",PRODUCT(M23,CPI!$B$112/P23)) -> 12885123
A24: The Final Countdown | B24: PG | C24: Action | D24: 1980 | E24: August 1, 1980 (United States) | F24: 6.7 | G24: 22000 | H24: Don Taylor | I24: Thomas Hunter | J24: Kirk Douglas | K24: United States | L24: 12000000 | M24: 16647800 | N24: Bryna Productions | O24: 103 | P24: {=_xlfn.XLOOKUP(D24, CPI!$A:A, CPI!$B:B)} -> 82.4 | Q24: =IF(M24="","",PRODUCT(M24,CPI!$B$112/P24)) -> 61560493
A25: Xanadu | B25: PG | C25: Fantasy | D25: 1980 | E25: August 8, 1980 (United States) | F25: 5.3 | G25: 12000 | H25: Robert Greenwald | I25: Richard Christian Danus | J25: Olivia Newton-John | K25: United States | L25: 20000000 | M25: 22762571 | N25: Universal Pictures | O25: 96 | P25: {=_xlfn.XLOOKUP(D25, CPI!$A:A, CPI!$B:B)} -> 82.4 | Q25: =IF(M25="","",PRODUCT(M25,CPI!$B$112/P25)) -> 84171789
A26: Urban Cowboy | B26: PG | C26: Drama | D26: 1980 | E26: June 6, 1980 (United States) | F26: 6.4 | G26: 14000 | H26: James Bridges | I26: Aaron Latham | J26: John Travolta | K26: United States | M26: 46918287 | N26: Paramount Pictures | O26: 132 | P26: {=_xlfn.XLOOKUP(D26, CPI!$A:A, CPI!$B:B)} -> 82.4 | Q26: =IF(M26="","",PRODUCT(M26,CPI!$B$112/P26)) -> 1.7349517e+08
A27: Altered States | B27: R | C27: Horror | D27: 1980 | E27: December 25, 1980 (United States) | F27: 6.9 | G27: 33000 | H27: Ken Russell | I27: Paddy Chayefsky | J27: William Hurt | K27: United States | M27: 19853892 | N27: Warner Bros. | O27: 102 | P27: {=_xlfn.XLOOKUP(D27, CPI!$A:A, CPI!$B:B)} -> 82.4 | Q27: =IF(M27="","",PRODUCT(M27,CPI!$B$112/P27)) -> 73416030
A28: Little Darlings | B28: R | C28: Comedy | D28: 1980 | E28: March 21, 1980 (United States) | F28: 6.5 | G28: 5100 | H28: Ron Maxwell | I28: Kimi Peck | J28: Tatum O'Neal | K28: United States | M28: 34326249 | N28: Stephen Friedman/Kings Road Productions | O28: 96 | P28: {=_xlfn.XLOOKUP(D28, CPI!$A:A, CPI!$B:B)} -> 82.4 | Q28: =IF(M28="","",PRODUCT(M28,CPI!$B$112/P28)) -> 1.2693214e+08
A29: Raise the Titanic | B29: PG | C29: Action | D29: 1980 | E29: August 1, 1980 (United States) | F29: 5 | G29: 4100 | H29: Jerry Jameson | I29: Adam Kennedy | J29: Jason Robards | K29: United Kingdom | L29: 36000000 | N29: ITC Films | O29: 115 | P29: {=_xlfn.XLOOKUP(D29, CPI!$A:A, CPI!$B:B)} -> 82.4 | Q29: =IF(M29="","",PRODUCT(M29,CPI!$B$112/P29))
A30: Brubaker | B30: R | C30: Crime | D30: 1980 | E30: June 20, 1980 (United States) | F30: 7.2 | G30: 17000 | H30: Stuart Rosenberg | I30: W.D. Richter | J30: Robert Redford | K30: United States | L30: 9000000 | M30: 37121708 | N30: Twentieth Century Fox | O30: 131 | P30: {=_xlfn.XLOOKUP(D30, CPI!$A:A, CPI!$B:B)} -> 82.4 | Q30: =IF(M30="","",PRODUCT(M30,CPI!$B$112/P30)) -> 1.3726923e+08
A31: American Gigolo | B31: R | C31: Crime | D31: 1980 | E31: February 1, 1980 (United States) | F31: 6.2 | G31: 22000 | H31: Paul Schrader | I31: Paul Schrader | J31: Richard Gere | K31: United States | L31: 4800000 | M31: 22743674 | N31: Paramount Pictures | O31: 117 | P31: {=_xlfn.XLOOKUP(D31, CPI!$A:A, CPI!$B:B)} -> 82.4 | Q31: =IF(M31="","",PRODUCT(M31,CPI!$B$112/P31)) -> 84101911
A32: My Bodyguard | B32: PG | C32: Comedy | D32: 1980 | E32: September 26, 1980 (United States) | F32: 7.1 | G32: 8900 | H32: Tony Bill | I32: Alan Ormsby | J32: Chris Makepeace | K32: United States | M32: 22482952 | N32: Twentieth Century Fox | O32: 102 | P32: {=_xlfn.XLOOKUP(D32, CPI!$A:A, CPI!$B:B)} -> 82.4 | Q32: =IF(M32="","",PRODUCT(M32,CPI!$B$112/P32)) -> 83137809
A33: Prom Night | B33: R | C33: Horror | D33: 1980 | E33: July 18, 1980 (United States) | F33: 5.4 | G33: 16000 | H33: Paul Lynch | I33: William Gray | J33: Leslie Nielsen | K33: Canada | M33: 14796236 | N33: Guardian Trust Company | O33: 92 | P33: {=_xlfn.XLOOKUP(D33, CPI!$A:A, CPI!$B:B)} -> 82.4 | Q33: =IF(M33="","",PRODUCT(M33,CPI!$B$112/P33)) -> 54713751
A34: Smokey and the Bandit II | B34: PG | C34: Action | D34: 1980 | E34: August 15, 1980 (United States) | F34: 5.3 | G34: 15000 | H34: Hal Needham | I34: Hal Needham | J34: Burt Reynolds | K34: United States | M34: 66132626 | N34: Universal Pictures | O34: 100 | P34: {=_xlfn.XLOOKUP(D34, CPI!$A:A, CPI!$B:B)} -> 82.4 | Q34: =IF(M34="","",PRODUCT(M34,CPI!$B$112/P34)) -> 2.4454625e+08
A35: Cattle Annie and Little Britches | B35: PG | C35: Drama | D35: 1980 | E35: April 24, 1981 (United States) | F35: 6.1 | G35: 604 | H35: Lamont Johnson | I35: David Eyre | J35: Scott Glenn | K35: United States | L35: 5100000 | M35: 534816 | N35: Cattle Annie Productions | O35: 97 | P35: {=_xlfn.XLOOKUP(D35, CPI!$A:A, CPI!$B:B)} -> 82.4 | Q35: =IF(M35="","",PRODUCT(M35,CPI!$B$112/P35)) -> 1977650.9
A36: Seems Like Old Times | B36: PG | C36: Comedy | D36: 1980 | E36: December 19, 1980 (United States) | F36: 6.7 | G36: 9100 | H36: Jay Sandrich | I36: Neil Simon | J36: Goldie Hawn | K36: United States | M36: 43995918 | N36: Rastar Films | O36: 102 | P36: {=_xlfn.XLOOKUP(D36, CPI!$A:A, CPI!$B:B)} -> 82.4 | Q36: =IF(M36="","",PRODUCT(M36,CPI!$B$112/P36)) -> 1.6268879e+08
A37: Private Benjamin | B37: R | C37: Comedy | D37: 1980 | E37: October 10, 1980 (United States) | F37: 6.2 | G37: 24000 | H37: Howard Zieff | I37: Nancy Meyers | J37: Goldie Hawn | K37: United States | L37: 10000000 | M37: 69847348 | N37: Warner Bros. | O37: 109 | P37: {=_xlfn.XLOOKUP(D37, CPI!$A:A, CPI!$B:B)} -> 82.4 | Q37: =IF(M37="","",PRODUCT(M37,CPI!$B$112/P37)) -> 2.5828261e+08
A38: The Hollywood Knights | B38: R | C38: Comedy | D38: 1980 | E38: May 30, 1980 (United States) | F38: 6.3 | G38: 4300 | H38: Floyd Mutrux | I38: Floyd Mutrux | J38: Tony Danza | K38: United States | L38: 4000000 | M38: 10000000 | N38: PolyGram Filmed Entertainment | O38: 91 | P38: {=_xlfn.XLOOKUP(D38, CPI!$A:A, CPI!$B:B)} -> 82.4 | Q38: =IF(M38="","",PRODUCT(M38,CPI!$B$112/P38)) -> 36978155
A39: Motel Hell | B39: R | C39: Comedy | D39: 1980 | E39: October 24, 1980 (United States) | F39: 6 | G39: 11000 | H39: Kevin Connor | I39: Robert Jaffe | J39: Rory Calhoun | K39: United States | L39: 3000000 | M39: 6342668 | N39: Camp Hill | O39: 101 | P39: {=_xlfn.XLOOKUP(D39, CPI!$A:A, CPI!$B:B)} -> 82.4 | Q39: =IF(M39="","",PRODUCT(M39,CPI!$B$112/P39)) -> 23454016
A40: The Jazz Singer | B40: PG | C40: Drama | D40: 1980 | E40: December 19, 1980 (United States) | F40: 5.9 | G40: 4000 | H40: Richard Fleischer | I40: Samson Raphaelson | J40: Laurence Olivier | K40: United States | M40: 27118000 | N40: EMI Films | O40: 115 | P40: {=_xlfn.XLOOKUP(D40, CPI!$A:A, CPI!$B:B)} -> 82.4 | Q40: =IF(M40="","",PRODUCT(M40,CPI!$B$112/P40)) -> 1.0027736e+08
A41: Coal Miner's Daughter | B41: PG | C41: Biography | D41: 1980 | E41: March 7, 1980 (United States) | F41: 7.5 | G41: 17000 | H41: Michael Apted | I41: Thomas Rickman | J41: Sissy Spacek | K41: United States | M41: 67182787 | N41: Universal Pictures | O41: 124 | P41: {=_xlfn.XLOOKUP(D41, CPI!$A:A, CPI!$B:B)} -> 82.4 | Q41: =IF(M41="","",PRODUCT(M41,CPI!$B$112/P41)) -> 2.4842955e+08
A42: The Watcher in the Woods | B42: PG | C42: Family | D42: 1980 | E42: October 9, 1981 (United States) | F42: 6.3 | G42: 5700 | H42: John Hough | I42: Brian Clemens | J42: Bette Davis | K42: United States | M42: 5000000 | N42: Walt Disney Productions | O42: 84 | P42: {=_xlfn.XLOOKUP(D42, CPI!$A:A, CPI!$B:B)} -> 82.4 | Q42: =IF(M42="","",PRODUCT(M42,CPI!$B$112/P42)) -> 18489078
A43: Breaker Morant | B43: PG | C43: Drama | D43: 1980 | E43: July 3, 1980 (Australia) | F43: 7.9 | G43: 13000 | H43: Bruce Beresford | I43: Jonathan Hardy | J43: Edward Woodward | K43: Australia | N43: The South Australian Film Corporation | O43: 107 | P43: {=_xlfn.XLOOKUP(D43, CPI!$A:A, CPI!$B:B)} -> 82.4 | Q43: =IF(M43="","",PRODUCT(M43,CPI!$B$112/P43))
A44: The Stunt Man | B44: R | C44: Action | D44: 1980 | E44: June 27, 1980 (United States) | F44: 7.1 | G44: 9000 | H44: Richard Rush | I44: Lawrence B. Marcus | J44: Peter O'Toole | K44: United States | L44: 3500000 | M44: 7063886 | N44: Melvin Simon Productions | O44: 131 | P44: {=_xlfn.XLOOKUP(D44, CPI!$A:A, CPI!$B:B)} -> 82.4 | Q44: =IF(M44="","",PRODUCT(M44,CPI!$B$112/P44)) -> 26120947
A45: Where the Buffalo Roam | B45: R | C45: Biography | D45: 1980 | E45: April 25, 1980 (United States) | F45: 6.6 | G45: 11000 | H45: Art Linson | I45: Hunter S. Thompson | J45: Peter Boyle | K45: United States | M45: 6659377 | N45: Universal Pictures | O45: 99 | P45: {=_xlfn.XLOOKUP(D45, CPI!$A:A, CPI!$B:B)} -> 82.4 | Q45: =IF(M45="","",PRODUCT(M45,CPI!$B$112/P45)) -> 24625148
A46: The Awakening | B46: R | C46: Horror | D46: 1980 | E46: October 31, 1980 (United States) | F46: 4.8 | G46: 2000 | H46: Mike Newell | I46: Allan Scott | J46: Charlton Heston | K46: United Kingdom | M46: 8415112 | N46: EMI Films | O46: 101 | P46: {=_xlfn.XLOOKUP(D46, CPI!$A:A, CPI!$B:B)} -> 82.4 | Q46: =IF(M46="","",PRODUCT(M46,CPI!$B$112/P46)) -> 31117532
A47: Cheech and Chong's Next Movie | B47: R | C47: Comedy | D47: 1980 | E47: July 18, 1980 (United States) | F47: 6.1 | G47: 12000 | H47: Tommy Chong | I47: Tommy Chong | J47: Cheech Marin | K47: United States | M47: 41675194 | N47: Universal Pictures | O47: 99 | P47: {=_xlfn.XLOOKUP(D47, CPI!$A:A, CPI!$B:B)} -> 82.4 | Q47: =IF(M47="","",PRODUCT(M47,CPI!$B$112/P47)) -> 1.5410718e+08
A48: The Island | B48: R | C48: Action | D48: 1980 | E48: June 13, 1980 (United States) | F48: 5.3 | G48: 3900 | H48: Michael Ritchie | I48: Peter Benchley | J48: Michael Caine | K48: United States | L48: 22000000 | M48: 15716828 | N48: Universal Pictures | O48: 109 | P48: {=_xlfn.XLOOKUP(D48, CPI!$A:A, CPI!$B:B)} -> 82.4 | Q48: =IF(M48="","",PRODUCT(M48,CPI!$B$112/P48)) -> 58117931
A49: The Boogey Man | B49: R | C49: Horror | D49: 1980 | E49: November 7, 1980 (United States) | F49: 4.6 | G49: 3900 | H49: Ulli Lommel | I49: Ulli Lommel | J49: Suzanna Love | K49: United States | L49: 300000 | N49: The Jerry Gross Organization | O49: 82 | P49: {=_xlfn.XLOOKUP(D49, CPI!$A:A, CPI!$B:B)} -> 82.4 | Q49: =IF(M49="","",PRODUCT(M49,CPI!$B$112/P49))
A50: The Nude Bomb | B50: PG | C50: Action | D50: 1980 | E50: May 9, 1980 (United States) | F50: 5.1 | G50: 3100 | H50: Clive Donner | I50: Mel Brooks | J50: Don Adams | K50: United States | L50: 15000000 | M50: 14662035 | N50: Universal Pictures | O50: 94 | P50: {=_xlfn.XLOOKUP(D50, CPI!$A:A, CPI!$B:B)} -> 82.4 | Q50: =IF(M50="","",PRODUCT(M50,CPI!$B$112/P50)) -> 54217501
A51: Lion of the Desert | B51: PG | C51: Biography | D51: 1980 | E51: May 16, 1981 (Japan) | F51: 8.3 | G51: 15000 | H51: Moustapha Akkad | I51: David Butler | J51: Anthony Quinn | K51: Libya | L51: 35000000 | N51: Falcon International Productions | O51: 173 | P51: {=_xlfn.XLOOKUP(D51, CPI!$A:A, CPI!$B:B)} -> 82.4 | Q51: =IF(M51="","",PRODUCT(M51,CPI!$B$112/P51))
A52: Stardust Memories | B52: PG | C52: Comedy | D52: 1980 | E52: September 26, 1980 (United States) | F52: 7.3 | G52: 22000 | H52: Woody Allen | I52: Woody Allen | J52: Woody Allen | K52: United States | L52: 10000000 | M52: 10389003 | N52: Jack Rollins & Charles H. Joffe Productions | O52: 89 | P52: {=_xlfn.XLOOKUP(D52, CPI!$A:A, CPI!$B:B)} -> 82.4 | Q52: =IF(M52="","",PRODUCT(M52,CPI!$B$112/P52)) -> 38416617
A53: Melvin and Howard | B53: R | C53: Comedy | D53: 1980 | E53: September 19, 1980 (United States) | F53: 6.8 | G53: 4500 | H53: Jonathan Demme | I53: Bo Goldman | J53: Paul Le Mat | K53: United States | L53: 7000000 | M53: 4309490 | N53: Universal Pictures | O53: 95 | P53: {=_xlfn.XLOOKUP(D53, CPI!$A:A, CPI!$B:B)} -> 82.4 | Q53: =IF(M53="","",PRODUCT(M53,CPI!$B$112/P53)) -> 15935699
A54: Can't Stop the Music | B54: PG | C54: Biography | D54: 1980 | E54: June 20, 1980 (United States) | F54: 4.2 | G54: 3700 | H54: Nancy Walker | I54: Bronte Woodard | J54: Ray Simpson | K54: United States | L54: 20000000 | N54: EMI Films | O54: 124 | P54: {=_xlfn.XLOOKUP(D54, CPI!$A:A, CPI!$B:B)} -> 82.4 | Q54: =IF(M54="","",PRODUCT(M54,CPI!$B$112/P54))
A55: Bronco Billy | B55: PG | C55: Action | D55: 1980 | E55: June 11, 1980 (United States) | F55: 6.1 | G55: 11000 | H55: Clint Eastwood | I55: Dennis Hackin | J55: Clint Eastwood | K55: United States | L55: 6500000 | M55: 24265659 | N55: Warner Bros. | O55: 116 | P55: {=_xlfn.XLOOKUP(D55, CPI!$A:A, CPI!$B:B)} -> 82.4 | Q55: =IF(M55="","",PRODUCT(M55,CPI!$B$112/P55)) -> 89729931
A56: City of Women | B56: R | C56: Comedy | D56: 1980 | E56: April 8, 1981 (United States) | F56: 7 | G56: 6700 | H56: Federico Fellini | I56: Federico Fellini | J56: Marcello Mastroianni | K56: Italy | M56: 12516 | N56: Opera Film Produzione | O56: 139 | P56: {=_xlfn.XLOOKUP(D56, CPI!$A:A, CPI!$B:B)} -> 82.4 | Q56: =IF(M56="","",PRODUCT(M56,CPI!$B$112/P56)) -> 46281.859
A57: The Private Eyes | B57: PG | C57: Comedy | D57: 1980 | E57: November 21, 1980 (United States) | F57: 6.7 | G57: 2900 | H57: Lang Elliott | I57: Tim Conway | J57: Tim Conway | K57: United States | N57: Tri Star Productions | O57: 91 | P57: {=_xlfn.XLOOKUP(D57, CPI!$A:A, CPI!$B:B)} -> 82.4 | Q57: =IF(M57="","",PRODUCT(M57,CPI!$B$112/P57))
A58: When Time Ran Out... | B58: PG | C58: Action | D58: 1980 | E58: March 28, 1980 (United States) | F58: 4.6 | G58: 2600 | H58: James Goldstone | I58: Gordon Thomas | J58: Paul Newman | K58: United States | L58: 20000000 | M58: 3763988 | N58: International Cinema | O58: 121 | P58: {=_xlfn.XLOOKUP(D58, CPI!$A:A, CPI!$B:B)} -> 82.4 | Q58: =IF(M58="","",PRODUCT(M58,CPI!$B$112/P58)) -> 13918533
A59: Oh Heavenly Dog | B59: PG | C59: Comedy | D59: 1980 | E59: July 11, 1980 (United States) | F59: 5.4 | G59: 2400 | H59: Joe Camp | I59: Rod Browning | J59: Chevy Chase | K59: United States | L59: 6000000 | M59: 6216067 | N59: Mulberry Square Productions | O59: 103 | P59: {=_xlfn.XLOOKUP(D59, CPI!$A:A, CPI!$B:B)} -> 82.4 | Q59: =IF(M59="","",PRODUCT(M59,CPI!$B$112/P59)) -> 22985869
A60: The Octagon | B60: R | C60: Action | D60: 1980 | E60: August 15, 1980 (United States) | F60: 5.1 | G60: 5200 | H60: Eric Karson | I60: Leigh Chapman | J60: Chuck Norris | K60: United States | L60: 4000000 | M60: 18971000 | N60: American Cinema Productions | O60: 103 | P60: {=_xlfn.XLOOKUP(D60, CPI!$A:A, CPI!$B:B)} -> 82.4 | Q60: =IF(M60="","",PRODUCT(M60,CPI!$B$112/P60)) -> 70151258
A61: Hangar 18 | B61: PG | C61: Sci-Fi | D61: 1980 | E61: March 13, 1981 (Ireland) | F61: 5.3 | G61: 2400 | H61: James L. Conway | I61: Ken Pettus | J61: Darren McGavin | K61: United States | L61: 11000000 | N61: Sunn Classic Pictures | O61: 97 | P61: {=_xlfn.XLOOKUP(D61, CPI!$A:A, CPI!$B:B)} -> 82.4 | Q61: =IF(M61="","",PRODUCT(M61,CPI!$B$112/P61))
A62: Herbie Goes Bananas | B62: G | C62: Adventure | D62: 1980 | E62: June 25, 1980 (United States) | F62: 5 | G62: 5300 | H62: Vincent McEveety | I62: Don Tait | J62: Charles Martin Smith | K62: United States | M62: 18000000 | N62: Walt Disney Productions | O62: 100 | P62: {=_xlfn.XLOOKUP(D62, CPI!$A:A, CPI!$B:B)} -> 82.4 | Q62: =IF(M62="","",PRODUCT(M62,CPI!$B$112/P62)) -> 66560680
A63: The Competition | B63: PG | C63: Drama | D63: 1980 | E63: December 3, 1980 (United States) | F63: 6.7 | G63: 1900 | H63: Joel Oliansky | I63: Joel Oliansky | J63: Richard Dreyfuss | K63: United States | M63: 14287755 | N63: Rastar Films | O63: 123 | P63: {=_xlfn.XLOOKUP(D63, CPI!$A:A, CPI!$B:B)} -> 82.4 | Q63: =IF(M63="","",PRODUCT(M63,CPI!$B$112/P63)) -> 52833482
A64: It's My Turn | B64: R | C64: Comedy | D64: 1980 | E64: February 5, 1981 (Argentina) | F64: 5.5 | G64: 875 | H64: Claudia Weill | I64: Eleanor Bergstein | J64: Jill Clayburgh | K64: United States | N64: Rastar Films | O64: 91 | P64: {=_xlfn.XLOOKUP(D64, CPI!$A:A, CPI!$B:B)} -> 82.4 | Q64: =IF(M64="","",PRODUCT(M64,CPI!$B$112/P64))
A65: Honeysuckle Rose | B65: PG | C65: Drama | D65: 1980 | E65: July 18, 1980 (United States) | F65: 6.3 | G65: 1400 | H65: Jerry Schatzberg | I65: Gösta Stevens | J65: Willie Nelson | K65: United States | M65: 17815212 | N65: Major Studio Partners | O65: 119 | P65: {=_xlfn.XLOOKUP(D65, CPI!$A:A, CPI!$B:B)} -> 82.4 | Q65: =IF(M65="","",PRODUCT(M65,CPI!$B$112/P65)) -> 65877368
A66: Resurrection | B66: PG | C66: Drama | D66: 1980 | E66: September 26, 1980 (United States) | F66: 7.3 | G66: 2800 | H66: Daniel Petrie | I66: Lewis John Carlino | J66: Ellen Burstyn | K66: United States | M66: 3910019 | N66: Universal Pictures | O66: 103 | P66: {=_xlfn.XLOOKUP(D66, CPI!$A:A, CPI!$B:B)} -> 82.4 | Q66: =IF(M66="","",PRODUCT(M66,CPI!$B$112/P66)) -> 14458529
A67: Fatso | B67: PG | C67: Comedy | D67: 1980 | E67: February 1, 1980 (United States) | F67: 6.3 | G67: 2000 | H67: Anne Bancroft | I67: Anne Bancroft | J67: Dom DeLuise | K67: United States | M67: 7653061 | N67: Brooksfilms | O67: 93 | P67: {=_xlfn.XLOOKUP(D67, CPI!$A:A, CPI!$B:B)} -> 82.4 | Q67: =IF(M67="","",PRODUCT(M67,CPI!$B$112/P67)) -> 28299608
A68: Moscow Does Not Believe in Tears | B68: PG | C68: Comedy | D68: 1980 | E68: February 11, 1980 (Soviet Union) | F68: 8.1 | G68: 12000 | H68: Vladimir Menshov | I68: Valentin Chernykh | J68: Vera Alentova | K68: Soviet Union | L68: 900000 | N68: Mosfilm | O68: 150 | P68: {=_xlfn.XLOOKUP(D68, CPI!$A:A, CPI!$B:B)} -> 82.4 | Q68: =IF(M68="","",PRODUCT(M68,CPI!$B$112/P68))
A69: The Fiendish Plot of Dr. Fu Manchu | B69: PG | C69: Comedy | D69: 1980 | E69: August 8, 1980 (United States) | F69: 5.1 | G69: 2000 | H69: Piers Haggard | I69: Rudy Dochtermann | J69: Peter Sellers | K69: United States | M69: 10697276 | N69: Braun Entertainment Group | O69: 100 | P69: {=_xlfn.XLOOKUP(D69, CPI!$A:A, CPI!$B:B)} -> 82.4 | Q69: =IF(M69="","",PRODUCT(M69,CPI!$B$112/P69)) -> 39556553
A70: Serial | B70: R | C70: Comedy | D70: 1980 | E70: March 28, 1980 (United States) | F70: 6.6 | G70: 915 | H70: Bill Persky | I70: Cyra McFadden | J70: Martin Mull | K70: United States | M70: 9870727 | N70: Paramount Pictures | O70: 86 | P70: {=_xlfn.XLOOKUP(D70, CPI!$A:A, CPI!$B:B)} -> 82.4 | Q70: =IF(M70="","",PRODUCT(M70,CPI!$B$112/P70)) -> 36500128
A71: Hero at Large | B71: PG | C71: Comedy | D71: 1980 | E71: February 8, 1980 (United States) | F71: 6 | G71: 1500 | H71: Martin Davidson | I71: AJ Carothers | J71: John Ritter | K71: United States | M71: 15934737 | N71: Kings Road Entertainment | O71: 98 | P71: {=_xlfn.XLOOKUP(D71, CPI!$A:A, CPI!$B:B)} -> 82.4 | Q71: =IF(M71="","",PRODUCT(M71,CPI!$B$112/P71)) -> 58923718
A72: Wholly Moses! | B72: PG | C72: Comedy | D72: 1980 | E72: June 13, 1980 (United States) | F72: 4.7 | G72: 1800 | H72: Gary Weis | I72: Guy Thomas | J72: Dudley Moore | K72: United States | M72: 14155617 | N72: Columbia Pictures | O72: 103 | P72: {=_xlfn.XLOOKUP(D72, CPI!$A:A, CPI!$B:B)} -> 82.4 | Q72: =IF(M72="","",PRODUCT(M72,CPI!$B$112/P72)) -> 52344860
A73: Bon Voyage, Charlie Brown (and Don't Come Back!!) | B73: G | C73: Animation | D73: 1980 | E73: May 30, 1980 (United States) | F73: 7.3 | G73: 2900 | H73: Bill Melendez | I73: Charles M. Schulz | J73: Scott Beach | K73: United States | M73: 2013193 | N73: Lee Mendelson Film Productions | O73: 75 | P73: {=_xlfn.XLOOKUP(D73, CPI!$A:A, CPI!$B:B)} -> 82.4 | Q73: =IF(M73="","",PRODUCT(M73,CPI!$B$112/P73)) -> 7444416.3
A74: In God We Trust (or Gimme That Prime Time Religion) | B74: PG | C74: Comedy | D74: 1980 | E74: September 26, 1980 (United States) | F74: 5.5 | G74: 965 | H74: Marty Feldman | I74: Marty Feldman | J74: Marty Feldman | K74: United States | M74: 5215015 | N74: Universal Pictures | O74: 97 | P74: {=_xlfn.XLOOKUP(D74, CPI!$A:A, CPI!$B:B)} -> 82.4 | Q74: =IF(M74="","",PRODUCT(M74,CPI!$B$112/P74)) -> 19284163
A75: Roadie | B75: PG | C75: Comedy | D75: 1980 | E75: June 13, 1980 (United States) | F75: 5.2 | G75: 1100 | H75: Alan Rudolph | I75: Big Boy Medlin | J75: Meat Loaf | K75: United States | M75: 4226370 | N75: Alive Enterprises | O75: 106 | P75: {=_xlfn.XLOOKUP(D75, CPI!$A:A, CPI!$B:B)} -> 82.4 | Q75: =IF(M75="","",PRODUCT(M75,CPI!$B$112/P75)) -> 15628337
A76: Just Tell Me What You Want | B76: R | C76: Comedy | D76: 1980 | E76: January 18, 1980 (United States) | F76: 5.5 | G76: 585 | H76: Sidney Lumet | I76: Jay Presson Allen | J76: Ali MacGraw | K76: United States | M76: 2086905 | N76: Warner Bros. | O76: 112 | P76: {=_xlfn.XLOOKUP(D76, CPI!$A:A, CPI!$B:B)} -> 82.4 | Q76: =IF(M76="","",PRODUCT(M76,CPI!$B$112/P76)) -> 7716989.7
A77: The Last Flight of Noah's Ark | B77: G | C77: Adventure | D77: 1980 | E77: June 25, 1980 (United States) | F77: 5.8 | G77: 1300 | H77: Charles Jarrott | I77: Ernest K. Gann | J77: Elliott Gould | K77: United States | L77: 6000000 | M77: 11000000 | N77: Walt Disney Productions | O77: 97 | P77: {=_xlfn.XLOOKUP(D77, CPI!$A:A, CPI!$B:B)} -> 82.4 | Q77: =IF(M77="","",PRODUCT(M77,CPI!$B$112/P77)) -> 40675971
A78: Little Miss Marker | B78: PG | C78: Comedy | D78: 1980 | E78: March 21, 1980 (United States) | F78: 6.3 | G78: 1400 | H78: Walter Bernstein | I78: Damon Runyon | J78: Walter Matthau | K78: United States | M78: 6321392 | N78: Universal Pictures | O78: 103 | P78: {=_xlfn.XLOOKUP(D78, CPI!$A:A, CPI!$B:B)} -> 82.4 | Q78: =IF(M78="","",PRODUCT(M78,CPI!$B$112/P78)) -> 23375342
A79: Willie & Phil | B79: R | C79: Comedy | D79: 1980 | E79: August 15, 1980 (United States) | F79: 5.9 | G79: 415 | H79: Paul Mazursky | I79: Jean Gruault | J79: Michael Ontkean | K79: United States | L79: 5500000 | M79: 4400000 | N79: Twentieth Century Fox | O79: 115 | P79: {=_xlfn.XLOOKUP(D79, CPI!$A:A, CPI!$B:B)} -> 82.4 | Q79: =IF(M79="","",PRODUCT(M79,CPI!$B$112/P79)) -> 16270388
A80: Babylon | C80: Drama | D80: 1980 | E80: November 1980 (United Kingdom) | F80: 7.4 | G80: 1300 | H80: Franco Rosso | I80: Franco Rosso | J80: David N. Haynes | K80: United Kingdom | M80: 109749 | N80: Diversity Music | O80: 95 | P80: {=_xlfn.XLOOKUP(D80, CPI!$A:A, CPI!$B:B)} -> 82.4 | Q80: =IF(M80="","",PRODUCT(M80,CPI!$B$112/P80)) -> 405831.56
A81: Windwalker | B81: PG | C81: Adventure | D81: 1980 | E81: November 18, 1983 (Sweden) | F81: 6.9 | G81: 1000 | H81: Kieth Merrill | I81: Ray Goldrup | J81: Trevor Howard | K81: United States | L81: 3000000 | N81: Santa Fe International | O81: 108 | P81: {=_xlfn.XLOOKUP(D81, CPI!$A:A, CPI!$B:B)} -> 82.4 | Q81: =IF(M81="","",PRODUCT(M81,CPI!$B$112/P81))
A82: Phobia | B82: R | C82: Drama | D82: 1980 | E82: September 9, 1980 (United States) | F82: 4 | G82: 546 | H82: John Huston | I82: Gary Sherman | J82: Paul Michael Glaser | K82: Canada | L82: 5100000 | M82: 59167 | N82: Borough Park Productions | O82: 94 | P82: {=_xlfn.XLOOKUP(D82, CPI!$A:A, CPI!$B:B)} -> 82.4 | Q82: =IF(M82="","",PRODUCT(M82,CPI!$B$112/P82)) -> 218788.65
A83: Windows | B83: R | C83: Drama | D83: 1980 | E83: January 18, 1980 (United States) | F83: 4.8 | G83: 643 | H83: Gordon Willis | I83: Barry Siegel | J83: Talia Shire | K83: United States | M83: 2128395 | N83: Mike Lobell Productions | O83: 96 | P83: {=_xlfn.XLOOKUP(D83, CPI!$A:A, CPI!$B:B)} -> 82.4 | Q83: =IF(M83="","",PRODUCT(M83,CPI!$B$112/P83)) -> 7870412.1
A84: Loving Couples | B84: PG | C84: Comedy | D84: 1980 | E84: October 24, 1980 (United States) | F84: 5.2 | G84: 351 | H84: Jack Smight | I84: Martin Donovan | J84: Shirley MacLaine | K84: United States | M84: 2806659 | N84: Time Life Films | O84: 97 | P84: {=_xlfn.XLOOKUP(D84, CPI!$A:A, CPI!$B:B)} -> 82.4 | Q84: =IF(M84="","",PRODUCT(M84,CPI!$B$112/P84)) -> 10378507
A85: The King and the Mockingbird | B85: Not Rated | C85: Animation | D85: 1980 | E85: March 19, 1980 (France) | F85: 7.9 | G85: 4800 | H85: Paul Grimault | I85: Hans Christian Andersen | J85: Jean Martin | K85: France | M85: 167451 | N85: Les Films Paul Grimault | O85: 83 | P85: {=_xlfn.XLOOKUP(D85, CPI!$A:A, CPI!$B:B)} -> 82.4 | Q85: =IF(M85="","",PRODUCT(M85,CPI!$B$112/P85)) -> 619202.91
A86: Oh, God! Book II | B86: PG | C86: Comedy | D86: 1980 | E86: October 3, 1980 (United States) | F86: 5.2 | G86: 2100 | H86: Gilbert Cates | I86: Josh Greenfeld | J86: George Burns | K86: United States | M86: 14504277 | N86: Warner Bros. | O86: 94 | P86: {=_xlfn.XLOOKUP(D86, CPI!$A:A, CPI!$B:B)} -> 82.4 | Q86: =IF(M86="","",PRODUCT(M86,CPI!$B$112/P86)) -> 53634141
A87: Those Lips, Those Eyes | B87: R | C87: Comedy | D87: 1980 | E87: August 15, 1980 (United States) | F87: 6.5 | G87: 269 | H87: Michael Pressman | I87: David Shaber | J87: Frank Langella | K87: United States | M87: 804713 | N87: Herb Jaffe | O87: 105 | P87: {=_xlfn.XLOOKUP(D87, CPI!$A:A, CPI!$B:B)} -> 82.4 | Q87: =IF(M87="","",PRODUCT(M87,CPI!$B$112/P87)) -> 2975680.2
A88: La Cage aux Folles II | B88: R | C88: Comedy | D88: 1980 | E88: February 15, 1981 (United States) | F88: 5.8 | G88: 1900 | H88: Édouard Molinaro | I88: Jean Poiret | J88: Michel Serrault | K88: France | M88: 6950125 | N88: Da.Ma. Cinematografica | O88: 102 | P88: {=_xlfn.XLOOKUP(D88, CPI!$A:A, CPI!$B:B)} -> 82.4 | Q88: =IF(M88="","",PRODUCT(M88,CPI!$B$112/P88)) -> 25700280
A89: The Gong Show Movie | B89: R | C89: Comedy | D89: 1980 | E89: May 23, 1980 (United States) | F89: 4.3 | G89: 740 | H89: Chuck Barris | I89: Chuck Barris | J89: Chuck Barris | K89: United States | M89: 6621520 | N89: Chuck Barris Productions | O89: 89 | P89: {=_xlfn.XLOOKUP(D89, CPI!$A:A, CPI!$B:B)} -> 82.4 | Q89: =IF(M89="","",PRODUCT(M89,CPI!$B$112/P89)) -> 24485160
A90: Gilda Live | B90: R | C90: Comedy | D90: 1980 | E90: March 28, 1980 (United States) | F90: 6.8 | G90: 599 | H90: Mike Nichols | I90: Anne Beatts | J90: Gilda Radner | K90: United States | M90: 2261507 | N90: Broadway Productions | O90: 96 | P90: {=_xlfn.XLOOKUP(D90, CPI!$A:A, CPI!$B:B)} -> 82.4 | Q90: =IF(M90="","",PRODUCT(M90,CPI!$B$112/P90)) -> 8362635.7
A91: Why Would I Lie? | B91: PG | C91: Comedy | D91: 1980 | E91: August 8, 1980 (United States) | F91: 6.5 | G91: 211 | H91: Larry Peerce | I91: Hollis Hodges | J91: Treat Williams | K91: United States | M91: 1175855 | N91: Metro-Goldwyn-Mayer (MGM) | O91: 105 | P91: {=_xlfn.XLOOKUP(D91, CPI!$A:A, CPI!$B:B)} -> 82.4 | Q91: =IF(M91="","",PRODUCT(M91,CPI!$B$112/P91)) -> 4348094.9
A92: First Family | B92: R | C92: Comedy | D92: 1980 | E92: December 25, 1980 (United States) | F92: 4.3 | G92: 593 | H92: Buck Henry | I92: Buck Henry | J92: Bob Newhart | K92: United States | M92: 15198912 | N92: F.F. Associates | O92: 97 | P92: {=_xlfn.XLOOKUP(D92, CPI!$A:A, CPI!$B:B)} -> 82.4 | Q92: =IF(M92="","",PRODUCT(M92,CPI!$B$112/P92)) -> 56202773
A93: Mantis Fist Fighter | C93: Action | D93: 1980 | E93: July 9, 1982 (United States) | F93: 6.7 | G93: 230 | H93: Wing-Cho Yip | I93: Hsin-Yi Chang | J93: Ka-Yan Leung | K93: Hong Kong | N93: East Asia Film Company | O93: 89 | P93: {=_xlfn.XLOOKUP(D93, CPI!$A:A, CPI!$B:B)} -> 82.4 | Q93: =IF(M93="","",PRODUCT(M93,CPI!$B$112/P93))
A94: Indiana Jones and the Raiders of the Lost Ark | B94: PG | C94: Action | D94: 1981 | E94: June 12, 1981 (United States) | F94: 8.4 | G94: 905000 | H94: Steven Spielberg | I94: Lawrence Kasdan | J94: Harrison Ford | K94: United States | L94: 18000000 | M94: 389925971 | N94: Paramount Pictures | O94: 115 | P94: {=_xlfn.XLOOKUP(D94, CPI!$A:A, CPI!$B:B)} -> 90.9 | Q94: =IF(M94="","",PRODUCT(M94,CPI!$B$112/P94)) -> 1.3070456e+09
A95: Body Heat | B95: R | C95: Crime | D95: 1981 | E95: August 28, 1981 (United States) | F95: 7.4 | G95: 32000 | H95: Lawrence Kasdan | I95: Lawrence Kasdan | J95: William Hurt | K95: United States | M95: 24058838 | N95: The Ladd Company | O95: 113 | P95: {=_xlfn.XLOOKUP(D95, CPI!$A:A, CPI!$B:B)} -> 90.9 | Q95: =IF(M95="","",PRODUCT(M95,CPI!$B$112/P95)) -> 80646072
A96: An American Werewolf in London | B96: R | C96: Comedy | D96: 1981 | E96: August 21, 1981 (United States) | F96: 7.5 | G96: 97000 | H96: John Landis | I96: John Landis | J96: David Naughton | K96: United Kingdom | L96: 10000000 | M96: 30669378 | N96: Polygram Pictures | O96: 97 | P96: {=_xlfn.XLOOKUP(D96, CPI!$A:A, CPI!$B:B)} -> 90.9 | Q96: =IF(M96="","",PRODUCT(M96,CPI!$B$112/P96)) -> 1.0280483e+08
A97: Escape from New York | B97: R | C97: Action | D97: 1981 | E97: July 10, 1981 (United States) | F97: 7.2 | G97: 131000 | H97: John Carpenter | I97: John Carpenter | J97: Kurt Russell | K97: United States | L97: 6000000 | M97: 25244626 | N97: AVCO Embassy Pictures | O97: 99 | P97: {=_xlfn.XLOOKUP(D97, CPI!$A:A, CPI!$B:B)} -> 90.9 | Q97: =IF(M97="","",PRODUCT(M97,CPI!$B$112/P97)) -> 84620875
A98: The Evil Dead | B98: NC-17 | C98: Horror | D98: 1981 | E98: April 15, 1983 (United States) | F98: 7.5 | G98: 192000 | H98: Sam Raimi | I98: Sam Raimi | J98: Bruce Campbell | K98: United States | L98: 350000 | M98: 2956630 | N98: Renaissance Pictures | O98: 85 | P98: {=_xlfn.XLOOKUP(D98, CPI!$A:A, CPI!$B:B)} -> 90.9 | Q98: =IF(M98="","",PRODUCT(M98,CPI!$B$112/P98)) -> 9910727.8
A99: Porky's | B99: R | C99: Comedy | D99: 1981 | E99: March 19, 1982 (United States) | F99: 6.2 | G99: 40000 | H99: Bob Clark | I99: Bob Clark | J99: Dan Monahan | K99: Canada | L99: 2500000 | M99: 111289673 | N99: Astral Bellevue Pathé | O99: 94 | P99: {=_xlfn.XLOOKUP(D99, CPI!$A:A, CPI!$B:B)} -> 90.9 | Q99: =IF(M99="","",PRODUCT(M99,CPI!$B$112/P99)) -> 3.730469e+08
A100: Blow Out | B100: R | C100: Crime | D100: 1981 | E100: July 24, 1981 (United States) | F100: 7.4 | G100: 47000 | H100: Brian De Palma | I100: Brian De Palma | J100: John Travolta | K100: United States | L100: 18000000 | M100: 12000000 | N100: Filmways Pictures | O100: 108 | P100: {=_xlfn.XLOOKUP(D100, CPI!$A:A, CPI!$B:B)} -> 90.9 | Q100: =IF(M100="","",PRODUCT(M100,CPI!$B$112/P100)) -> 40224422
A101: Clash of the Titans | B101: PG | C101: Action | D101: 1981 | E101: June 12, 1981 (United States) | F101: 6.9 | G101: 42000 | H101: Desmond Davis | I101: Beverley Cross | J101: Laurence Olivier | K101: United Kingdom | L101: 15000000 | M101: 41092328 | N101: Charles H. Schneer Productions | O101: 118 | P101: {=_xlfn.XLOOKUP(D101, CPI!$A:A, CPI!$B:B)} -> 90.9 | Q101: =IF(M101="","",PRODUCT(M101,CPI!$B$112/P101)) -> 1.3774293e+08
A102: Excalibur | B102: R | C102: Adventure | D102: 1981 | E102: April 10, 1981 (United States) | F102: 7.4 | G102: 59000 | H102: John Boorman | I102: Thomas Malory | J102: Nigel Terry | K102: United Kingdom | L102: 11000000 | M102: 34971136 | N102: Cinema '84 | O102: 140 | P102: {=_xlfn.XLOOKUP(D102, CPI!$A:A, CPI!$B:B)} -> 90.9 | Q102: =IF(M102="","",PRODUCT(M102,CPI!$B$112/P102)) -> 1.1722448e+08
A103: Mad Max 2 | B103: R | C103: Action | D103: 1981 | E103: May 21, 1982 (United States) | F103: 7.6 | G103: 170000 | H103: George Miller | I103: Terry Hayes | J103: Mel Gibson | K103: Australia | L103: 3000000 | M103: 23668369 | N103: Kennedy Miller Productions | O103: 96 | P103: {=_xlfn.XLOOKUP(D103, CPI!$A:A, CPI!$B:B)} -> 90.9 | Q103: =IF(M103="","",PRODUCT(M103,CPI!$B$112/P103)) -> 79337206
...
